.coveragerc
.editorconfig
.flake8
.gitignore
.pre-commit-config.yaml
LICENSE.rst
README.md
mypy.ini
pyproject.toml
readme_empirical_score.png
readme_heatmap_bounded_perturbation.png
readme_heatmap_empirical_score.png
readme_heatmap_inpainted.png
readme_heatmap_trained_score.png
readme_nplan.png
readme_samples.png
readme_trained_score.png
ruff.toml
setup.py
.github/workflows/CI.yml
.github/workflows/publish.yml
configs/__init__.py
configs/default_config.py
configs/example.py
diffusionjax/__init__.py
diffusionjax/_version.py
diffusionjax/inverse_problems.py
diffusionjax/models.py
diffusionjax/plot.py
diffusionjax/run_lib.py
diffusionjax/sde.py
diffusionjax/solvers.py
diffusionjax/utils.py
diffusionjax.egg-info/PKG-INFO
diffusionjax.egg-info/SOURCES.txt
diffusionjax.egg-info/dependency_links.txt
diffusionjax.egg-info/requires.txt
diffusionjax.egg-info/top_level.txt
diffusionjax/models/__init__.py
diffusionjax/models/networks_edm2.py
examples/example.py
examples/example1.py
examples/example2.py
test/__init__.py
test/test_solvers.py
test/test_utils.py
test/external/test_benchmark.py