Metadata-Version: 2.2
Name: diffusionjax
Version: 0.1.8
Summary: diffusionjax is a simple and accessible diffusion models package in JAX
Home-page: https://github.com/bb515/diffusionjax
Author: Benjamin Boys and Jakiw Pidstrigach
License: MIT
Requires-Dist: numpy
Requires-Dist: scipy
Requires-Dist: matplotlib
Requires-Dist: flax
Requires-Dist: ml_collections
Requires-Dist: tqdm
Requires-Dist: absl-py
Requires-Dist: wandb
Provides-Extra: linting
Requires-Dist: flake8; extra == "linting"
Requires-Dist: pylint; extra == "linting"
Requires-Dist: mypy; extra == "linting"
Requires-Dist: typing-extensions; extra == "linting"
Requires-Dist: pre-commit; extra == "linting"
Requires-Dist: ruff; extra == "linting"
Requires-Dist: jaxtyping; extra == "linting"
Provides-Extra: testing
Requires-Dist: optax; extra == "testing"
Requires-Dist: orbax-checkpoint; extra == "testing"
Requires-Dist: torch; extra == "testing"
Requires-Dist: pytest; extra == "testing"
Requires-Dist: pytest-xdist; extra == "testing"
Requires-Dist: pytest-cov; extra == "testing"
Requires-Dist: coveralls; extra == "testing"
Requires-Dist: jax>=0.4.1; extra == "testing"
Requires-Dist: jaxlib>=0.4.1; extra == "testing"
Requires-Dist: setuptools_scm[toml]; extra == "testing"
Requires-Dist: setuptools_scm_git_archive; extra == "testing"
Provides-Extra: examples
Requires-Dist: optax; extra == "examples"
Requires-Dist: orbax-checkpoint; extra == "examples"
Requires-Dist: torch; extra == "examples"
Requires-Dist: mlkernels; extra == "examples"
Dynamic: author
Dynamic: description
Dynamic: description-content-type
Dynamic: home-page
Dynamic: license
Dynamic: provides-extra
Dynamic: requires-dist
Dynamic: summary
